MANIFEST.in
README.rst
setup.py
ProjeoEDE.egg-info/PKG-INFO
ProjeoEDE.egg-info/SOURCES.txt
ProjeoEDE.egg-info/dependency_links.txt
ProjeoEDE.egg-info/top_level.txt
eosModules/__init__.py
eosModules/my_package.py
eosModules/bar/__init__.py
eosModules/bar/my_package2.py
eosModules/foo/__init__.py
eosModules/foo/my_package3.py