Metadata-Version: 1.0
Name: ProjeoEDE
Version: 0.3
Summary: Example package that calculate thermodynamic data
Home-page: UNKNOWN
Author: Jhonnatha de Andrade Monteiro
Author-email: jhonnatha.am@gmail.com
License: MIT
Platform: UNKNOWN
